idgraph/__init__.py
idgraph-0.0.1.dist-info/AUTHORS.rst
idgraph-0.0.1.dist-info/LICENSE
idgraph-0.0.1.dist-info/METADATA
idgraph-0.0.1.dist-info/WHEEL
idgraph-0.0.1.dist-info/top_level.txt
idgraph-0.0.1.dist-info/RECORD
