Metadata-Version: 2.1
Name: idgraph
Version: 0.0.1
Summary: Provides IPython cell magic for dgraph queries, mutations,  and alteration remote execution.
Home-page: https://github.com/jbn/idgraph
Author: John Bjorn Nelson
Author-email: jbn@abreka.com
License: MIT license
Keywords: idgraph
Platform: UNKNOWN
Classifier: Development Status :: 2 - Pre-Alpha
Classifier: Intended Audience :: Developers
Classifier: License :: OSI Approved :: MIT License
Classifier: Natural Language :: English
Classifier: Programming Language :: Python :: 3
Classifier: Programming Language :: Python :: 3.5
Classifier: Programming Language :: Python :: 3.6
Classifier: Programming Language :: Python :: 3.7
Requires-Python: >=3, !=3.0.*, !=3.1.*, !=3.2.*, !=3.3.*, !=3.4.*
